<annotation>
	<folder>MaskDataset</folder>
	<filename>images (16).jpg</filename>
	<path>/Users/mehmetekin/Downloads/MaskDataset/images (16).jpg</path>
	<source>
		<database>Unknown</database>
	</source>
	<size>
		<width>284</width>
		<height>177</height>
		<depth>3</depth>
	</size>
	<segmented>0</segmented>
	<object>
		<name>FaceMask</name>
		<pose>Unspecified</pose>
		<truncated>0</truncated>
		<difficult>0</difficult>
		<bndbox>
			<xmin>52</xmin>
			<ymin>79</ymin>
			<xmax>113</xmax>
			<ymax>127</ymax>
		</bndbox>
	</object>
</annotation>
